epythet/__init__.py
epythet/autogen.py
epythet/call_make.py
epythet/cli.py
epythet/config_parser.py
epythet/docs_gen.py
epythet/setup_docsrc.py
epythet/templates.py
epythet/_static/docsrc/.gitignore
epythet/_static/docsrc/Makefile
epythet/_static/docsrc/conf.py
epythet/_static/docsrc/make.bat
epythet/tools/__init__.py
epythet/tools/docstring_diagnosis.py
epythet/tools/published_docs.py
epythet-0.1.10.dist-info/LICENSE
epythet-0.1.10.dist-info/METADATA
epythet-0.1.10.dist-info/WHEEL
epythet-0.1.10.dist-info/entry_points.txt
epythet-0.1.10.dist-info/top_level.txt
epythet-0.1.10.dist-info/RECORD
