Metadata-Version: 2.1
Name: epythet
Version: 0.1.10
Summary: Tools for documentation and packaging
Home-page: https://github.com/i2mint/epythet
Author-email: andie.phan@analog.com
License: Apache Software License
Keywords: documentation,publishing
Platform: any
License-File: LICENSE
Requires-Dist: Sphinx>=3.3.1
Requires-Dist: myst-parser>=0.15.2
Requires-Dist: argh>=0.26.2
Requires-Dist: commonmark>=0.9.1
Requires-Dist: sphinx-toggleprompt>=0.0.5
Requires-Dist: sphinx-copybutton>=0.4.0
Requires-Dist: sphinx-rtd-theme>=1.0.0
Requires-Dist: dol
Requires-Dist: pandas
Requires-Dist: requests
Requires-Dist: hubcap
